gala/__init__.py
gala/_cconfig.cpython-313-x86_64-linux-gnu.so
gala/_compat_utils.py
gala/_compiler.c
gala/_version.py
gala/cconfig.pyx
gala/compiler_version.cpython-313-x86_64-linux-gnu.so
gala/conftest.py
gala/extra_compile_macros.h
gala/io.py
gala/logging.py
gala/setup_package.py
gala/units.py
gala/util.py
gala/coordinates/__init__.py
gala/coordinates/gd1.py
gala/coordinates/greatcircle.py
gala/coordinates/helpers.py
gala/coordinates/jhelum.py
gala/coordinates/magellanic_stream.py
gala/coordinates/oph.py
gala/coordinates/orphan.py
gala/coordinates/pal13.py
gala/coordinates/pal5.py
gala/coordinates/pm_cov_transform.py
gala/coordinates/poincarepolar.py
gala/coordinates/reflex.py
gala/coordinates/sgr.py
gala/coordinates/velocity_frame_transforms.py
gala/coordinates/tests/SgrCoord.cpp
gala/coordinates/tests/SgrCoord.h
gala/coordinates/tests/SgrCoord_data
gala/coordinates/tests/Vasiliev2020-Sagittarius-subset.csv
gala/coordinates/tests/__init__.py
gala/coordinates/tests/c_pm.npy
gala/coordinates/tests/gd1_coord.txt
gala/coordinates/tests/idl_vgsr_vhel.txt
gala/coordinates/tests/pm_cov.npy
gala/coordinates/tests/sergey_orphan.txt
gala/coordinates/tests/test_all_streamframes.py
gala/coordinates/tests/test_gd1.py
gala/coordinates/tests/test_greatcircle.py
gala/coordinates/tests/test_jhelum.py
gala/coordinates/tests/test_orphan.py
gala/coordinates/tests/test_pal5.py
gala/coordinates/tests/test_pm_cov_transform.py
gala/coordinates/tests/test_reflex.py
gala/coordinates/tests/test_sgr.py
gala/coordinates/tests/test_velocity_frame_transforms.py
gala/dynamics/__init__.py
gala/dynamics/core.py
gala/dynamics/nonlinear.py
gala/dynamics/orbit.py
gala/dynamics/plot.py
gala/dynamics/representation_nd.py
gala/dynamics/setup_package.py
gala/dynamics/util.py
gala/dynamics/actionangle/__init__.py
gala/dynamics/actionangle/actionangle_o2gf.py
gala/dynamics/actionangle/actionangle_staeckel.py
gala-1.10.1.dist-info/METADATA
gala-1.10.1.dist-info/WHEEL
gala-1.10.1.dist-info/top_level.txt
gala-1.10.1.dist-info/RECORD
gala-1.10.1.dist-info/licenses/AUTHORS.rst
gala-1.10.1.dist-info/licenses/LICENSE
