Metadata-Version: 2.4
Name: gala
Version: 1.10.1
Summary: Galactic dynamics in Python
Author-email: Adrian Price-Whelan <adrianmpw@gmail.com>
License: The MIT License (MIT)
Project-URL: Documentation, https://gala.adrian.pw
Project-URL: Repository, https://github.com/adrn/gala.git
Keywords: astronomy,dynamics
Classifier: Development Status :: 5 - Production/Stable
Classifier: Programming Language :: Python
Classifier: Topic :: Scientific/Engineering :: Astronomy
Requires-Python: >=3.10
License-File: LICENSE
License-File: AUTHORS.rst
Requires-Dist: numpy>=1.26.4
Requires-Dist: scipy>=1.12
Requires-Dist: astropy>=6.0
Requires-Dist: pyyaml
Requires-Dist: cython>=0.29
Provides-Extra: shared
Requires-Dist: matplotlib; extra == "shared"
Requires-Dist: numexpr; extra == "shared"
Requires-Dist: h5py; extra == "shared"
Requires-Dist: tqdm; extra == "shared"
Provides-Extra: test
Requires-Dist: gala[shared]; extra == "test"
Requires-Dist: pytest; extra == "test"
Requires-Dist: pytest-astropy; extra == "test"
Provides-Extra: extra
Requires-Dist: galpy; extra == "extra"
Requires-Dist: sympy; extra == "extra"
Requires-Dist: twobody; extra == "extra"
Requires-Dist: scipy<1.15; extra == "extra"
Provides-Extra: docs
Requires-Dist: gala[extra,shared]; extra == "docs"
Requires-Dist: numpydoc; extra == "docs"
Requires-Dist: ipykernel; extra == "docs"
Requires-Dist: jupyter-client; extra == "docs"
Requires-Dist: nbsphinx; extra == "docs"
Requires-Dist: ipython_genutils; extra == "docs"
Requires-Dist: pydata_sphinx_theme; extra == "docs"
Requires-Dist: sphinx; extra == "docs"
Requires-Dist: sphinxcontrib-bibtex; extra == "docs"
Requires-Dist: sphinx-astrorefs; extra == "docs"
Requires-Dist: sphinx_automodapi; extra == "docs"
Requires-Dist: sphinx_astropy; extra == "docs"
Requires-Dist: rtds_action; extra == "docs"
Requires-Dist: requests; extra == "docs"
Provides-Extra: tutorials
Requires-Dist: gala[extra,shared]; extra == "tutorials"
Requires-Dist: IPython; extra == "tutorials"
Requires-Dist: nbconvert; extra == "tutorials"
Requires-Dist: ipython_genutils; extra == "tutorials"
Requires-Dist: jupyter_client; extra == "tutorials"
Requires-Dist: ipykernel; extra == "tutorials"
Requires-Dist: jupytext; extra == "tutorials"
Requires-Dist: pyia>=1.4; extra == "tutorials"
Requires-Dist: astroquery; extra == "tutorials"
Provides-Extra: dev
Requires-Dist: gala[docs,extra,test,tutorials]; extra == "dev"
Requires-Dist: pre-commit; extra == "dev"
Dynamic: license-file
